baicao/__init__.py
baicao-0.3.1.dist-info/licenses/LICENCE
baicao-0.3.1.dist-info/METADATA
baicao-0.3.1.dist-info/WHEEL
baicao-0.3.1.dist-info/top_level.txt
baicao-0.3.1.dist-info/RECORD
