Metadata-Version: 2.4
Name: baicao
Version: 0.3.1
Summary: A module for Bài cào — a Vietnamese basic card game
Author-email: Ngô Trần Quang Thiện <quangthienngotran@gmail.com>
License:                     GNU GENERAL PUBLIC LICENSE
Keywords: card,cards,baicao,Vietnamese
Requires-Python: >=3.7
License-File: LICENCE
Dynamic: license-file
